alita_login/__init__.py
alita_login/config.py
alita_login/manager.py
alita_login/mixins.py
alita_login/security.py
alita_login/signals.py
alita_login/utils.py
alita_login-0.1.0.dist-info/METADATA
alita_login-0.1.0.dist-info/RECORD
alita_login-0.1.0.dist-info/WHEEL
alita_login-0.1.0.dist-info/top_level.txt
